README.md
setup.py
music_tag/__init__.py
music_tag/__main__.py
music_tag/aac.py
music_tag/aiff.py
music_tag/apev2.py
music_tag/asf.py
music_tag/dsf.py
music_tag/file.py
music_tag/flac.py
music_tag/id3.py
music_tag/mp4.py
music_tag/smf.py
music_tag/util.py
music_tag/vorbis.py
music_tag/wave.py
music_tag.egg-info/PKG-INFO
music_tag.egg-info/SOURCES.txt
music_tag.egg-info/dependency_links.txt
music_tag.egg-info/requires.txt
music_tag.egg-info/top_level.txt
music_tag.egg-info/zip-safe
test/test.py
test/test_append.py
test/test_fresh_set.py
test/test_get.py
test/test_rm.py
test/test_set.py