Metadata-Version: 2.1
Name: music-tag
Version: 0.4.0
Summary: Simple interface to edit audio file metadata
Home-page: https://github.com/KristoforMaynard/music-tag
Author: Kristofor Maynard
Author-email: kristofor.maynard@gmail.com
License: MIT
Download-URL: https://github.com/KristoforMaynard/music-tag/archive/0.4.0.zip
Keywords: music,metadata,id3
Platform: UNKNOWN
Classifier: Programming Language :: Python :: 3
Classifier: Programming Language :: Python :: 3.3
Classifier: Programming Language :: Python :: 3.4
Classifier: Programming Language :: Python :: 3.5
Classifier: Programming Language :: Python :: 3.6
Classifier: Programming Language :: Python :: 3.7
Classifier: License :: OSI Approved :: MIT License
Classifier: Operating System :: OS Independent
Provides-Extra: artwork
